[
	{
		"name": "Double Room with Shared Bathroom",
		"image": "/images/DeluxeK.jpg",
		"bed": "1 Double Bed"
	},
	{
		"name": "Superior King Room",
		"image": "/images/King.jpg",
		"bed": "1 extra large Double Bed or 1 Single Bed"
	},
	{
		"name": "Standard Double Room with Shared Bathroom",
		"image": "/images/room44.jpeg",
		"bed": "1 Double Bed"
	},
	{
		"name": "Single Room",
		"image": "/images/single.jpg",
		"bed": "1 Single Bed"
	},
	{
		"name": "Deluxe King Room",
		"image": "/images/bedroovaluebg.jpeg",
		"bed": "1 Large Double Bed"
	},
	{
		"name": "Double Room with Private Bathroom",
		"image": "/images/room4.jpeg",
		"bed": "1 Double Bed"
	},
	{
		"name": "King Room",
		"image": "/images/bed1.jpeg",
		"bed": "1 Extra-Large Double Bed"
	},
	{
		"name": "Double Room with Shared Bathroom",
		"image": "/images/view1.jpeg",
		"bed": "1 Double Bed"
	}
]
